carbonara/__init__.py
carbonara/bibtex.py
carbonara/constants.py
carbonara/icon.png
carbonara/protocols.conf
carbonara/protocols/__init__.py
carbonara/protocols/protocol_sampling_sequence.py
carbonara/tests/__init__.py
carbonara/tests/test_protocol_carbonara_sampling_sequence.py
carbonara/viewers/__init__.py
carbonara/viewers/carbonara_sampling_sequence_viewer.py
carbonara/wizards/__init__.py
carbonara/wizards/wizard_carbonara.py
scipion_em_carbonara-0.0.1.dist-info/LICENSE
scipion_em_carbonara-0.0.1.dist-info/METADATA
scipion_em_carbonara-0.0.1.dist-info/WHEEL
scipion_em_carbonara-0.0.1.dist-info/entry_points.txt
scipion_em_carbonara-0.0.1.dist-info/top_level.txt
scipion_em_carbonara-0.0.1.dist-info/RECORD
