Metadata-Version: 2.1
Name: scipion-em-carbonara
Version: 0.0.1
Summary: Plugin to run CARBonAra within the Scipion framework
Author-email: Roberto Marabini <roberto@cnb.csic.es>, Marta Martinez <mmmtnez@cnb.csic.es>
License: GNU General Public License v3 (GPLv3)
Project-URL: Homepage, https://github.com/scipion-em/scipion-em-carbonara
Project-URL: Repository, https://github.com/scipion-em/scipion-em-carbonara
Project-URL: Issues, https://github.com/scipion-em/scipion-em-carbonara/issues
Keywords: scipion,electron-microscopy,cryo-em,structural-biology,image-processing,scipion-3.0,carbonara
Requires-Python: >=3.8
License-File: LICENSE
Requires-Dist: scipion-pyworkflow
Requires-Dist: scipion-em
